{
  "ABOUT": "About",
  "ABOUT_HARMONOID": "About Harmonoid",
  "ADD": "Add",
  "ADDED_ENTRY_TO_PLAYLIST": "Added \"\"ENTRY\"\" to \"\"PLAYLIST\"\"",
  "ADDED_FOLDERS": "Added folders:",
  "ADDED_M_OF_N_FILES": "Added \"M\" of \"N\" files...",
  "ADDED_N_ENTRIES_TO_PLAYLIST": "Added \"N\" entries to \"\"PLAYLIST\"\"",
  "ADDING_YOUR_MUSIC": "Adding your music...",
  "ADD_NEW_FOLDER": "Add new folder",
  "ADD_NEW_FOLDER_SUBTITLE": "Add a new folder into the media library",
  "ADD_PLAYLIST_TO_NOW_PLAYING": "Add playlist to now playing",
  "ADD_THIS_FOLDER": "Add this folder",
  "ADD_TO_NOW_PLAYING": "Add to now playing",
  "ADD_TO_PLAYLIST": "Add to playlist",
  "ALBUM": "Album",
  "ALBUMS": "Albums",
  "ALBUM_ARTIST": "Album artist",
  "ALBUM_ARTISTS": "Album artists",
  "ALL_FILES": "All files",
  "ANIMATION_SPEED": "Animation speed:",
  "ARTIST": "Artist",
  "ARTISTS": "Artists",
  "ASCENDING": "Ascending",
  "AVAILABLE_STORAGES": "Available storages",
  "A_TO_Z": "A to Z",
  "BACK": "Back",
  "BETA": "Beta",
  "BUFFERING": "Buffering...",
  "CANCEL": "Cancel",
  "CENTER": "Center",
  "CLEAR_LRC_FILE": "Clear selected LRC file",
  "CLEAR_SELECTION": "Clear selection",
  "COMING_UP": "Coming up",
  "CONFIGURE_VISIBLE_TABS_SUBTITLE": "Choose which tabs appear in the media library",
  "CONFIGURE_VISIBLE_TABS_TITLE": "Configure visible tabs",
  "CONNECT": "Connect",
  "CONNECTED": "Connected",
  "CONTROL_PANEL": "Control panel",
  "COPY_AS_JSON": "Copy as JSON",
  "COPY_LINK": "Copy link",
  "CORRUPT_LRC_FILE": "Selected LRC file is corrupt. Please verify the file & try again.",
  "COUNT": "Count",
  "CREATE": "Create",
  "CREATE_NEW_PLAYLIST": "Create new playlist",
  "CROSSFADE": "Crossfade",
  "CROSSFADE_BETWEEN_TRACKS": "Crossfade between tracks",
  "CROSSFADE_DURATION": "Crossfade duration:",
  "CROSSFADE_EXCLUSIVE_AUDIO_ERROR": "Exclusive audio is not supported with crossfade",
  "DATE_ADDED": "Date added",
  "DEFAULT": "Default",
  "DELETE": "Delete",
  "DEMO_HINT": "(Demo)",
  "DESCENDING": "Descending",
  "DEVELOPER": "Developer",
  "DISCONNECT": "Disconnect",
  "DISCOVERING_FILES": "Discovering files...",
  "DISPLAY_ARTIST_IMAGES": "Display artist images",
  "DISPLAY_AUDIO_FORMAT": "Display audio format",
  "DISPLAY_PROGRESS_ON_TASKBAR": "Display progress on taskbar",
  "DISPLAY_UPON_PLAYBACK": "Display upon playback",
  "DISPLAY_VOLUME_SLIDER": "Display volume slider",
  "DONE": "Done",
  "EDIT": "Edit",
  "EDIT_ALBUM_PARAMETERS_SUBTITLE": "Edit parameters used to uniquely identify an album",
  "EDIT_ALBUM_PARAMETERS_TITLE": "Edit album parameters",
  "EDIT_DETAILS": "Edit details",
  "EDIT_MINIMUM_FILE_SIZE": "Edit minimum file size",
  "EDIT_TAGS": "Edit tags",
  "EMAIL": "Email",
  "ENABLE_ANIMATION_EFFECTS": "Enable animation effects",
  "ENABLE_DISCORD_RPC": "Enable Discord RPC",
  "ENABLE_NOTIFICATION_LYRICS": "Enable notification lyrics",
  "ENABLE_NOW_PLAYING_RIPPLE_EFFECT": "Enable \"Now playing screen\" ripple effect",
  "END": "End",
  "ENTRIES": "Entries",
  "ENTRY": "Entry",
  "ERROR": "Error",
  "EXCLUSIVE_AUDIO": "Exclusive audio",
  "EXIT_FULLSCREEN": "Exit fullscreen",
  "EXIT_NOW_PLAYING": "Exit now playing",
  "EXIT_SUBTITLE": "Do you want to exit Harmonoid?",
  "EXIT_TITLE": "Exit",
  "FILE": "File",
  "FILES": "Files",
  "FILE_INFORMATION": "File information",
  "FILE_PATH_OR_URL": "Enter file path or URL",
  "FIND": "Find",
  "FOLDER": "Folder",
  "FOLDERS": "Folders",
  "FOLDERS_NO_ITEMS_SUBTITLE": "This folder is empty",
  "FOLDERS_NO_ITEMS_TITLE": "No files found",
  "FOLDER_NOT_FOUND": "This folder could not be located",
  "FOLLOW_ON_X": "Follow on \"X\"",
  "FULLSCREEN": "Enter fullscreen",
  "GENRE": "Genre",
  "GENRES": "Genres",
  "GITHUB": "GitHub",
  "GO_TO_SETTINGS": "Go to settings",
  "GRID": "Grid",
  "HIDE": "Hide",
  "HIDE_HIDDEN_FILES": "Hide hidden files",
  "HIDE_LYRICS": "Hide lyrics",
  "HISTORY": "History",
  "IMAGES": "Images",
  "IMPORT": "Import",
  "LASTFM": "Last.fm",
  "LAST_DIRECTORY_REMOVED": "At least one folder needs to stay",
  "LESS": "Less",
  "LICENSE": "License",
  "LIKED_SONGS": "Liked songs",
  "LINKED_AS_X": "Linked as \"\"X\"\"",
  "LINK_YOUR_ACCOUNT": "Link your account",
  "LIST": "List",
  "LOGIN": "Login",
  "LOGOUT": "Logout",
  "LOOKUP_FOR_FALLBACK_COVERS": "Lookup for fallback covers",
  "LOOKUP_FOR_LRC_IN_DIRECTORY": "Lookup for .LRC in directory",
  "LYRICS": "Lyrics",
  "LYRICS_ALIGNMENT": "Lyrics alignment",
  "LYRICS_FONT_FAMILY": "Lyrics font family",
  "LYRICS_NOT_FOUND": "Lyrics not found.",
  "LYRICS_RETRIEVING": "Retrieving lyrics...",
  "LYRICS_SIZE": "Lyrics size:",
  "MATERIAL_DESIGN": "Material Design",
  "MEDIA_FILES": "Media files",
  "MEDIA_LIBRARY": "Media library",
  "MEDIA_LIBRARY_INACCESSIBLE_FOLDERS_SUBTITLE": "Few of the folders from your media library could not be accessed.\nMaybe their location is changed or access to them is revoked by the \"OPERATING_SYSTEM\".\nPlease remove these folders before proceeding & add them again afterwards.",
  "MEDIA_LIBRARY_INACCESSIBLE_FOLDERS_TITLE": "Inaccessible folders",
  "MEDIA_LIBRARY_NO_ITEMS_SUBTITLE": "Change where to look for the music from settings",
  "MEDIA_LIBRARY_NO_ITEMS_TITLE": "No music found",
  "MEDIA_LIBRARY_REFRESHING_DIALOG_SUBTITLE": "The media library is being refreshed. Please wait for it to complete.",
  "MENU": "Menu",
  "MIX": "Mix",
  "MOBILE_ALBUM_GRID_SIZE": "Album grid size",
  "MOBILE_ARTIST_GRID_SIZE": "Artist grid size",
  "MOBILE_GENRE_GRID_SIZE": "Genre grid size",
  "MODIFY_BACKGROUND_IMAGES": "Modify background images",
  "MONO": "Mono",
  "MORE": "More",
  "MUTE": "Mute",
  "M_ALBUMS_AND_N_TRACKS": "\"M\" albums & \"N\" tracks",
  "M_FOLDERS_AND_N_FILES": "\"M\" folders & \"N\" files",
  "NEXT": "Next",
  "NO": "No",
  "NOTHING_IN_QUEUE": "There's nothing in the queue",
  "NOW_PLAYING": "Now playing",
  "NOW_YOU_ARE_GOOD_TO_GO_BACK": "Now you're good to go back",
  "NO_FOLDERS_ADDED": "No folders added",
  "NO_PLAYLISTS_FOUND": "No playlists found.\nCreate some to see them there.",
  "N_ALBUMS": "\"N\" Albums",
  "N_ALBUMS_ONE_TRACK": "\"N\" albums & one track",
  "N_ARTISTS": "\"N\" Artists",
  "N_CHANNELS": "\"N\" Channels",
  "N_ENTRIES": "\"N\" Entries",
  "N_FILES": "\"N\" files",
  "N_FOLDERS": "\"N\" folders",
  "N_FOLDERS_AND_ONE_FILE": "\"N\" folders & one file",
  "N_GENRES": "\"N\" Genres",
  "N_ITEMS_SELECTED": "\"N\" items selected",
  "N_TRACKS": "\"N\" Tracks",
  "OFF": "Off",
  "OK": "Okay",
  "ONE_ALBUM": "One album",
  "ONE_ALBUM_N_TRACKS": "One album & \"N\" tracks",
  "ONE_ALBUM_ONE_TRACK": "One album & one track",
  "ONE_ARTIST": "One artist",
  "ONE_FILE": "One file",
  "ONE_FOLDER": "One folder",
  "ONE_FOLDER_AND_N_FILES": "One folder & \"N\" files",
  "ONE_FOLDER_AND_ONE_FILE": "One folder & one file",
  "ONE_GENRE": "One genre",
  "ONE_TRACK": "One track",
  "OPEN_FILE_OR_URL": "Open file or URL",
  "OPEN_IN_BROWSER": "Open in browser",
  "OPTIONS": "Options",
  "ORDER": "Order",
  "OTP": "One-Time Code",
  "OTP_SEND": "Send One-Time Code",
  "OTP_SEND_FAILURE": "Couldn't send One-Time Code.",
  "OTP_SEND_SUCCESS": "One-Time Code Sent. Please check your email.",
  "OTP_VERIFY": "Verify One-Time Code",
  "OTP_VERIFY_FAILURE": "Couldn't verify One-Time Code",
  "OTP_VERIFY_SUCCESS": "One-Time Code Verified",
  "PAUSE": "Pause",
  "PAUSED": "Paused",
  "PERMISSION_IMAGES_AND_PHOTOS": "Images & photos",
  "PERMISSION_IMAGES_AND_PHOTOS_SUBTITLE": "For in-directory fallback album arts.\nAndroid 13+ separates photos' permission.",
  "PERMISSION_MUSIC_AND_AUDIO": "Music & audio",
  "PERMISSION_MUSIC_AND_AUDIO_SUBTITLE": "For playing & managing media library",
  "PERMISSION_NOTIFICATIONS": "Notifications",
  "PERMISSION_NOTIFICATIONS_SUBTITLE": "For displaying synced lyrics",
  "PHONE": "Phone",
  "PITCH": "Pitch",
  "PLAY": "Play",
  "PLAYING": "Playing",
  "PLAYLIST": "Playlist",
  "PLAYLISTS": "Playlists",
  "PLAYLIST_ADD_DIALOG_SUBTITLE": "Select a playlist to add this item",
  "PLAYLIST_ADD_DIALOG_TITLE": "Add to playlist",
  "PLAYLIST_CREATE_DIALOG_SUBTITLE": "Enter name for the playlist",
  "PLAYLIST_DELETE_DIALOG_SUBTITLE": "Delete the playlist \"\"NAME\"\"?",
  "PLAYLIST_ENTRY_REMOVE_DIALOG_SUBTITLE": "Remove \"\"ENTRY\"\" from \"\"PLAYLIST\"\"?",
  "PLAYLIST_RENAME_DIALOG_SUBTITLE": "Enter name for the playlist",
  "PLAY_ALL": "Play all",
  "PLAY_NEXT": "Play next",
  "PLAY_NOW": "Play now",
  "PLAY_URL": "Play URL",
  "PLAY_URL_SUBTITLE": "Enter URI to the media resource",
  "PREAMP_GAIN": "Pre-amp gain",
  "PREVIOUS": "Previous",
  "PRIVACY": "Privacy",
  "PROCEED": "Proceed",
  "PROPERTY": "Property",
  "QUIT_HARMONOID": "Quit Harmonoid",
  "READ": "Read",
  "READ_METADATA": "Read metadata",
  "RECOMMENDATIONS": "Suggestions",
  "RECOMMENDED_HINT": "(Recommended)",
  "REFRESH": "Refresh",
  "REFRESH_MEDIA_LIBRARY_UPON_START": "Refresh on app launch",
  "REFRESH_SUBTITLE": "Check for new & deleted files",
  "REINDEX": "Reindex",
  "REINDEX_SUBTITLE": "Build the media library database again",
  "REINDEX_WARNING": "This option clears the media library database and rescans all files. Use \"REFRESH\" to check only for added or removed files.",
  "REMOVE": "Remove",
  "REMOVE_FROM_PLAYLIST": "Remove from playlist",
  "RENAME": "Rename",
  "REPEAT": "Repeat",
  "REPLAYGAIN": "ReplayGain",
  "RESET_PITCH": "Reset pitch",
  "RESET_SPEED": "Reset speed",
  "RESTORE": "Restore",
  "RESTORE_DEFAULTS": "Restore defaults",
  "RESULTS_FOR_QUERY": "Results for \"\"QUERY\"\"",
  "SAVE": "Save",
  "SAVE_AS_PLAYLIST": "Save as playlist",
  "SD_CARD": "SD Card",
  "SEARCH": "Search",
  "SEARCH_BANNER_NO_ITEMS_SUBTITLE": "Nothing like that could be found in your media library",
  "SEARCH_BANNER_NO_ITEMS_TITLE": "No results",
  "SEARCH_BANNER_SUBTITLE": "Search your music...",
  "SEARCH_BANNER_TITLE": "Find",
  "SEARCH_HINT": "Search...",
  "SEE_ALL": "See all",
  "SELECT": "Select",
  "SETTINGS": "Settings",
  "SETTINGS_SECTION_DISPLAY_SUBTITLE": "Configure application's visual appearance & behavior",
  "SETTINGS_SECTION_DISPLAY_TITLE": "Display",
  "SETTINGS_SECTION_LANGUAGE_INFO": "Help improve your language support here",
  "SETTINGS_SECTION_LANGUAGE_SUBTITLE": "Choose the preferred language",
  "SETTINGS_SECTION_LANGUAGE_TITLE": "Language",
  "SETTINGS_SECTION_LASTFM_SUBTITLE": "Configure connection to Last.fm",
  "SETTINGS_SECTION_LASTFM_TITLE": "Last.fm",
  "SETTINGS_SECTION_MEDIA_LIBRARY_SUBTITLE": "Configure how the media files are organized",
  "SETTINGS_SECTION_MEDIA_LIBRARY_TITLE": "Media library",
  "SETTINGS_SECTION_MISCELLANEOUS_SUBTITLE": "Other options that can be configured",
  "SETTINGS_SECTION_MISCELLANEOUS_TITLE": "Miscellaneous",
  "SETTINGS_SECTION_NOW_PLAYING_SUBTITLE": "Configure behavior of the \"Now playing\"",
  "SETTINGS_SECTION_NOW_PLAYING_TITLE": "Now playing",
  "SETTINGS_SECTION_PERMISSIONS_SUBTITLE": "Grant additional permissions to enhance the experience",
  "SETTINGS_SECTION_PERMISSIONS_TITLE": "Permissions",
  "SETTINGS_SECTION_PLUS_SUBTITLE": "Little extra, for those who keep this alive",
  "SETTINGS_SECTION_STATS_SUBTITLE": "Statistical details about the media library",
  "SETTINGS_SECTION_STATS_TITLE": "Stats",
  "SET_LRC_FILE": "Set LRC file",
  "SHARE": "Share",
  "SHOW_ALBUM": "Show album",
  "SHOW_ARTIST": "Show artist",
  "SHOW_ARTISTS": "Show artists",
  "SHOW_HIDDEN_FILES": "Show hidden files",
  "SHOW_IN_FILE_MANAGER": "Show in file manager",
  "SHOW_LYRICS": "Show lyrics",
  "SHOW_NOW_PLAYING_SCREEN": "Show \"Now playing screen\"",
  "SHUFFLE": "Shuffle",
  "SORT": "Sort",
  "SORT_BY": "Sort by",
  "SPEED": "Speed",
  "START": "Start",
  "START_MIX_AFTER_ENDING": "Start mix after ending",
  "STEREO": "Stereo",
  "SUBSCRIPTION_EXPIRED_SUBTITLE": "Couldn't verify your access",
  "SUBSCRIPTION_EXPIRED_TITLE": "Membership expired",
  "TAG_EDITOR": "Tag editor",
  "TAG_EDITOR_ADD_PROPERTY": "Add property",
  "TAG_EDITOR_ERROR_SAVE": "Couldn't save the file. Please share a sample file.",
  "TAG_EDITOR_ERROR_SET_COVER": "Couldn't set the cover. Please share a sample file.",
  "TAG_EDITOR_ERROR_UNKNOWN_AUDIO_FILE": "Can't edit the tags for this file. Please share a sample file.",
  "TAG_EDITOR_ERROR_UNKNOWN_IMAGE_FILE": "Invalid image. Please share a sample file.",
  "TAG_EDITOR_EXPORT_COVER": "Export cover",
  "TAG_EDITOR_FILL_FROM_INTERNET": "Fill from internet",
  "TAG_EDITOR_KEY": "Key: \"KEY\"",
  "TAG_EDITOR_NO_TAGS_SUBTITLE": "Add tags to organize this file",
  "TAG_EDITOR_NO_TAGS_TITLE": "No tags found",
  "TAG_EDITOR_REMOVE_COVER": "Remove cover",
  "TAG_EDITOR_REMOVE_PROPERTY": "Remove property",
  "TAG_EDITOR_REVERT_COVER": "Revert cover",
  "TAG_EDITOR_SEPARATORS_INFO": "Use these characters to separate multiple values: ; / \\ \\\\ or //",
  "TAG_EDITOR_SET_COVER": "Set cover",
  "TAG_EDITOR_UNSAVED_CHANGES_DIALOG_SUBTITLE": "You have unsaved changes. Do you want to save them?",
  "THEME": "Theme",
  "THEME_MODE_DARK": "Dark",
  "THEME_MODE_LIGHT": "Light",
  "THEME_MODE_SYSTEM": "System",
  "TITLE": "Title",
  "TRACK": "Track",
  "TRACKS": "Tracks",
  "TRACKS_DELETE_DIALOG_SUBTITLE": "Delete \"N\" tracks?",
  "TRACK_DELETE_DIALOG_SUBTITLE": "Delete the track \"\"NAME\"\"?",
  "TRACK_NUMBER": "Track number",
  "TYPE": "Type",
  "UNMUTE": "Unmute",
  "UNSELECT": "Unselect",
  "UPDATE_AVAILABLE": "Update available",
  "URL": "URL",
  "USE_COLOR_PALETTE": "Use color palette",
  "USE_SYSTEM_COLOR_SCHEME": "Use system color scheme",
  "VALUE": "Value",
  "VOLUME_BOOST": "Volume boost",
  "WARNING": "Warning",
  "X": "X",
  "YEAR": "Year",
  "YES": "Yes"
}
